{
  "version": "0.3.14-fixed",
  "steps": [
    {
      "tag": "CreateField",
      "model": "Project",
      "field": "name",
      "type": "String",
      "arity": "Required"
    },
    {
      "tag": "CreateField",
      "model": "Project",
      "field": "description",
      "type": "String",
      "arity": "Optional"
    },
    {
      "tag": "CreateField",
      "model": "Project",
      "field": "completed",
      "type": "Boolean",
      "arity": "Required"
    },
    {
      "tag": "CreateDirective",
      "location": {
        "path": {
          "tag": "Field",
          "model": "Project",
          "field": "completed"
        },
        "directive": "default"
      }
    },
    {
      "tag": "CreateArgument",
      "location": {
        "tag": "Directive",
        "path": {
          "tag": "Field",
          "model": "Project",
          "field": "completed"
        },
        "directive": "default"
      },
      "argument": "",
      "value": "false"
    },
    {
      "tag": "CreateField",
      "model": "Task",
      "field": "description",
      "type": "String",
      "arity": "Required"
    },
    {
      "tag": "CreateField",
      "model": "Task",
      "field": "notes",
      "type": "String",
      "arity": "Optional"
    },
    {
      "tag": "CreateField",
      "model": "Task",
      "field": "completed",
      "type": "Boolean",
      "arity": "Required"
    },
    {
      "tag": "CreateDirective",
      "location": {
        "path": {
          "tag": "Field",
          "model": "Task",
          "field": "completed"
        },
        "directive": "default"
      }
    },
    {
      "tag": "CreateArgument",
      "location": {
        "tag": "Directive",
        "path": {
          "tag": "Field",
          "model": "Task",
          "field": "completed"
        },
        "directive": "default"
      },
      "argument": "",
      "value": "false"
    },
    {
      "tag": "DeleteField",
      "model": "Task",
      "field": "name"
    },
    {
      "tag": "CreateField",
      "model": "Resource",
      "field": "description",
      "type": "String",
      "arity": "Optional"
    }
  ]
}